flask_oidc_keycloak/__init__.py
flask_oidc_keycloak/discovery.py
flask_oidc_keycloak/jwks.py
flask_oidc_keycloak/registration.py
flask_oidc_keycloak/registration_util.py
flask_oidc_keycloak/utils.py
flask_oidc_keycloak/validation.py
flask_oidc_keycloak-0.6.2.dist-info/LICENSE.txt
flask_oidc_keycloak-0.6.2.dist-info/METADATA
flask_oidc_keycloak-0.6.2.dist-info/WHEEL
flask_oidc_keycloak-0.6.2.dist-info/entry_points.txt
flask_oidc_keycloak-0.6.2.dist-info/top_level.txt
flask_oidc_keycloak-0.6.2.dist-info/RECORD
