Metadata-Version: 2.1
Name: flask-oidc-keycloak
Version: 0.6.2
Summary: OpenID Connect extension for Flask - Keycloak
Home-page: https://github.com/vucanews/flask-oidc-keycloak
Author: Erica Ehrhardt, Patrick Uiterwijk, Lars Wilhelmsen, Tyler Banks
Author-email: tyler@vucanews.com
License: UNKNOWN
Platform: UNKNOWN
Classifier: Environment :: Web Environment
Classifier: Framework :: Flask
Classifier: Intended Audience :: Developers
Classifier: License :: OSI Approved :: BSD License
Classifier: Operating System :: OS Independent
Classifier: Programming Language :: Python
Classifier: Programming Language :: Python :: 3
Classifier: Programming Language :: Python :: 3.4
Classifier: Programming Language :: Python :: 3.5
Classifier: Programming Language :: Python :: 3.6
Classifier: Topic :: Internet :: WWW/HTTP :: Dynamic Content
Classifier: Topic :: Software Development :: Libraries :: Python Modules
License-File: LICENSE.txt
Requires-Dist: Flask
Requires-Dist: itsdangerous
Requires-Dist: oauth2client
Requires-Dist: six
Requires-Dist: python-jwt
Requires-Dist: jwcrypto
Requires-Dist: cachetools
Provides-Extra: dev
Requires-Dist: twine ; extra == 'dev'
Requires-Dist: tox ; extra == 'dev'
Requires-Dist: bumpversion ; extra == 'dev'
Requires-Dist: nose ; extra == 'dev'
Requires-Dist: nosy ; extra == 'dev'
